COPYRIGHT
CREDITS
GPL-LICENSE.txt
LICENSE
MIT-LICENSE.txt
OSL-LICENSE.txt
README
TODO
ez_setup.py
setup.cfg
setup.py
solu/__init__.py
solu/application.py
solu/manage.py
solu/models.py
solu/utils.py
solu/views.py
solu.egg-info/PKG-INFO
solu.egg-info/SOURCES.txt
solu.egg-info/dependency_links.txt
solu.egg-info/entry_points.txt
solu.egg-info/not-zip-safe
solu.egg-info/requires.txt
solu.egg-info/top_level.txt
solu/static/crosshair.png
solu/static/favicon.ico
solu/static/jquery-1.2.6.min.js
solu/static/jquery-ui-personalized-1.5.2.min.js
solu/static/map.png
solu/static/site.css
solu/templates/add.html
solu/templates/base.html
solu/templates/delete.html
solu/templates/edit.html
solu/templates/index.html
solu/templates/map.html
solu/templates/search_results.html
solu/templates/show.html
tests/__init__.py
tests/deploy.ini
tests/test_models.py
tests/test_views.py