Metadata-Version: 1.0
Name: solu
Version: 0.1
Summary: Self-service Office resource Locator and Updater
Home-page: http://www.heikkitoivonen.net/solu/
Author: Heikki Toivonen
Author-email: My first name at heikkitoivonen.net
License: The Open Software License 3.0
Platform: any
Classifier: Development Status :: 3 - Alpha
Classifier: License :: OSI Approved :: MIT License
Classifier: License :: OSI Approved :: GNU General Public License (GPL)
Classifier: Operating System :: OS Independent
Classifier: Programming Language :: Python
Classifier: Programming Language :: JavaScript
Classifier: Topic :: Internet :: WWW/HTTP :: WSGI :: Application
Classifier: Topic :: Office/Business
